Single_Cycle.v
// Program Counter
module Program_Counter(
    input clk, reset,
    input      [31:0] PC_in,
    output reg [31:0] PC_out
);

always @(posedge clk) begin
if(reset)
    PC_out <= 32'b0;
else 
    PC_out <= PC_in;
end 

endmodule

// PC + 4
module PCplus4(
    input [31:0] fromPC, 
    output [31:0] NextoPC
    );
    assign NextoPC = fromPC + 4;
endmodule

// Instruction Memory
module Instruction_Memory(
    input clk, reset,
    input [31:0] read_addresss,
    output [31:0] instruction_out
);

reg [7:0] IMEM [0:1024];
wire [31:0] InstAddr;
integer i;

assign InstAddr = read_addresss & 32'hfffffffc; // word alignment
assign instruction_out = {IMEM[InstAddr+3], IMEM[InstAddr+2], IMEM[InstAddr+1], IMEM[InstAddr]};

always @(posedge clk) begin
    if(reset) begin
        for (i = 0; i < 1024; i = i + 4) begin
            {IMEM[i+3], IMEM[i+2], IMEM[i+1], IMEM[i]} <= 32'b0;  // Reset all memory locations
        end
    end
end
endmodule

// Register File
module Reg_File(
    input clk, reset, RegWrite,
    input [4:0] Rs1, Rs2, Rd,
    input [31:0] Write_data,
    output [31:0] read_data1, read_data2
);

reg [31:0] Registers [0:31];
integer i;

always @(posedge clk) begin
    if (reset) begin
        for(i=0; i <= 32; i=i+1) begin
            Registers[i] <= 32'b0;
        end 
    end else if(RegWrite) begin
        Registers[Rd] <= Write_data;
    end
end

assign read_data1 = (Rs1 == 0) ? 32'h00000000 : Registers[Rs1];
assign read_data2 = (Rs2 == 0) ? 32'h00000000 : Registers[Rs2];

endmodule

// immediate Generator
module ImmGen(
    input [31:0] instruction,
    output reg [31:0] immExt
);
    wire opcode = instruction[6:0];

always @(*) begin
    case(opcode)
    7'b0000011, 7'b0010011 : immExt <= {{20{instruction[31]}}, instruction[31:20]}; // l-type
    7'b0100011 : immExt <= {{20{instruction[31]}}, instruction[31:25], instruction[11:7]}; // s-type
    7'b1100011 : immExt <= {{19{instruction[31]}}, instruction[31], instruction[7], instruction[30:25], instruction[11:8], 1'b0}; // b-type
    7'b1101111 : immExt <= {{11{instruction[31]}}, instruction[31], instruction[19:12], instruction[20], instruction[30:21], 1'b0}; // J-type
    default: immExt = 32'b0;
    endcase 
end 

endmodule

// control unit
module Control_Unit(
    input [6:0] opcode,
    output reg Branch, MemRead, MemtoReg, MemWrite, ALUSrc, RegWrite,
    output reg [1:0] ALUOp
);

always @(*) begin
    case(opcode)
    7'b0110011 : {ALUSrc, MemtoReg, RegWrite, MemRead, MemWrite, Branch, ALUOp} <= 8'b001000_10; // R-type
    7'b0010011, 7'b0000011 : {ALUSrc, MemtoReg, RegWrite, MemRead, MemWrite, Branch, ALUOp} <= 8'b111100_00; // I-type
    7'b0100011 : {ALUSrc, MemtoReg, RegWrite, MemRead, MemWrite, Branch, ALUOp} <= 8'b100010_00; // S-type
    7'b1100011 : {ALUSrc, MemtoReg, RegWrite, MemRead, MemWrite, Branch, ALUOp} <= 8'b000001_01; // B-type
    7'b1101111 : {ALUSrc, MemtoReg, RegWrite, MemRead, MemWrite, Branch, ALUOp} <= 8'b000001_01; // J-type
    default : {ALUSrc, MemtoReg, RegWrite, MemRead, MemWrite, Branch, ALUOp} <= 8'b000000_00;
    endcase
end 
endmodule

module ALU_unit(
    input [31:0] A, B, 
    input [3:0] Control_in, 
    output reg [31:0] ALU_Result,
    output reg zero
);

always @(*) begin
    case(Control_in)
    4'b0000 : begin zero <= 0; ALU_Result <= A + B; end // add
    4'b0001 : begin zero <= 0; ALU_Result <= A - B; end // sub
    4'b0010 : begin zero <= 0; ALU_Result <= A * B; end // mul
    4'b0011 : begin zero <= 0; ALU_Result <= A / B; end // div
    4'b0100 : begin if(A==B) zero <= 1; else zero <= 0; ALU_Result <= A - B; end // beq
    4'b0101 : begin if(A<B) zero <= 1; else zero <= 0; ALU_Result <= A - B; end // blt
    4'b0110 : begin if(A>=B) zero <= 1; else zero <= 0; ALU_Result <= A - B; end // bge
    4'b0111 : begin zero <= 0; ALU_Result <= A - B; end // jal
    endcase 
end 

endmodule

tb.v
`timescale 1ns/1ps

module Program_Counter_tb;
    reg clk, reset;
    reg [31:0] PC_in;
    wire [31:0] PC_out;

    Program_Counter dut (
        .clk(clk),
        .reset(reset),
        .PC_in(PC_in),
        .PC_out(PC_out)
    );

    always #5 clk = ~clk; // 10 ns period

    initial begin 
        $dumpfile("Program_Counter.vcd");
        $dumpvars(0, Program_Counter_tb);
        

        // Initialize signals
        clk = 0;
        reset = 1;  // Start with reset active
        PC_in = 32'h00000000;  // Default PC value

        #10 reset = 0;

        // Test Case 1: Normal PC update
        #10 PC_in = 32'h00000004;  // Set PC to 4
        #10 PC_in = 32'h00000008;  // Set PC to 8
        #10 PC_in = 32'h0000000C;  // Set PC to 12

        // Test Case 2: Reset behavior
        #10 reset = 1;  // Apply reset
        #10 reset = 0;  // Remove reset

        // Test Case 3: Another normal PC update
        #10 PC_in = 32'h00000010;  // Set PC to 16
        #10 PC_in = 32'h00000014;  // Set PC to 20
        #20 $finish;  // Stop simulation after all tests
    end 
    initial begin
        $monitor("Time=%0t | Reset=%b | PC_in=%h | PC_out=%h",
                  $time, reset, PC_in, PC_out);
    end

endmodule

Program_Counter.vcd
$date
	Tue Feb  4 12:14:35 2025
$end
$version
	Icarus Verilog
$end
$timescale
	1ps
$end
$scope module Program_Counter_tb $end
$var wire 32 ! PC_out [31:0] $end
$var reg 32 " PC_in [31:0] $end
$var reg 1 # clk $end
$var reg 1 $ reset $end
$scope module dut $end
$var wire 32 % PC_in [31:0] $end
$var wire 1 # clk $end
$var wire 1 $ reset $end
$var reg 32 & PC_out [31:0] $end
$upscope $end
$upscope $end
$enddefinitions $end
#0
$dumpvars
bx &
b0 %
1$
0#
b0 "
bx !
$end
#5000
b0 !
b0 &
1#
#10000
0#
0$
#15000
1#
#20000
0#
b100 "
b100 %
#25000
b100 !
b100 &
1#
#30000
0#
b1000 "
b1000 %
#35000
b1000 !
b1000 &
1#
#40000
0#
b1100 "
b1100 %
#45000
b1100 !
b1100 &
1#
#50000
0#
1$
#55000
b0 !
b0 &
1#
#60000
0#
0$
#65000
b1100 !
b1100 &
1#
#70000
0#
b10000 "
b10000 %
#75000
b10000 !
b10000 &
1#
#80000
0#
b10100 "
b10100 %
#85000
b10100 !
b10100 &
1#
